robustrankaggregpy/__init__.py
robustrankaggregpy/aggregate_ranks.py
robustrankaggregpy/py.typed
robustrankaggregpy-0.1.0.dist-info/WHEEL
robustrankaggregpy-0.1.0.dist-info/METADATA
robustrankaggregpy-0.1.0.dist-info/RECORD
