Metadata-Version: 2.3
Name: robustrankaggregpy
Version: 0.1.0
Summary: Implementation of the Robust Rank Aggregation R package in Python
Author: Braden Griebel
Author-email: Braden Griebel <bgriebel@uw.edu>
Requires-Dist: numpy>=2.2.6
Requires-Dist: pandas>=2.3.3
Requires-Dist: scipy>=1.15.3
Requires-Python: >=3.10
